area_of_shapes_by_ishraq/__init__.py
area_of_shapes_by_ishraq/area.py
area_of_shapes_by_ishraq-0.0.1.dist-info/METADATA
area_of_shapes_by_ishraq-0.0.1.dist-info/WHEEL
area_of_shapes_by_ishraq-0.0.1.dist-info/top_level.txt
area_of_shapes_by_ishraq-0.0.1.dist-info/RECORD
